kaiheilacardbuilder_m-1.3.0.dist-info/METADATA
kaiheilacardbuilder_m-1.3.0.dist-info/WHEEL
kaiheilacardbuilder_m-1.3.0.dist-info/licenses/LICENSE
khl_card/__init__.py
khl_card/accessory.py
khl_card/builder.py
khl_card/card.py
khl_card/color.py
khl_card/modules.py
khl_card/types.py
kaiheilacardbuilder_m-1.3.0.dist-info/RECORD
