Metadata-Version: 2.1
Name: KaiheilaCardBuilder-M
Version: 1.3.0
Summary: 一个构建开黑啦卡片的工具
Author-Email: DancingSnow <1121149616@qq.com>, kexue <xana278@foxmail.com>
License: MIT License
Requires-Python: >=3.10
